README.md
setup.py
brynq_sdk_acerta/__init__.py
brynq_sdk_acerta/acerta.py
brynq_sdk_acerta/addresses.py
brynq_sdk_acerta/agreements.py
brynq_sdk_acerta/bank_accounts.py
brynq_sdk_acerta/code_lists.py
brynq_sdk_acerta/company_cars.py
brynq_sdk_acerta/contact_information.py
brynq_sdk_acerta/cost_centers.py
brynq_sdk_acerta/employees.py
brynq_sdk_acerta/employees_additional_information.py
brynq_sdk_acerta/employer.py
brynq_sdk_acerta/family_members.py
brynq_sdk_acerta/family_situation.py
brynq_sdk_acerta/inservice.py
brynq_sdk_acerta/salaries.py
brynq_sdk_acerta.egg-info/PKG-INFO
brynq_sdk_acerta.egg-info/SOURCES.txt
brynq_sdk_acerta.egg-info/dependency_links.txt
brynq_sdk_acerta.egg-info/not-zip-safe
brynq_sdk_acerta.egg-info/requires.txt
brynq_sdk_acerta.egg-info/top_level.txt
brynq_sdk_acerta/schemas/__init__.py
brynq_sdk_acerta/schemas/address.py
brynq_sdk_acerta/schemas/agreement.py
brynq_sdk_acerta/schemas/bank_account.py
brynq_sdk_acerta/schemas/company_car.py
brynq_sdk_acerta/schemas/contact_information.py
brynq_sdk_acerta/schemas/cost_center.py
brynq_sdk_acerta/schemas/employee.py
brynq_sdk_acerta/schemas/employer.py
brynq_sdk_acerta/schemas/family.py
brynq_sdk_acerta/schemas/in_service.py
brynq_sdk_acerta/schemas/in_service_config.py
brynq_sdk_acerta/schemas/planning.py
brynq_sdk_acerta/schemas/salaries.py