Metadata-Version: 1.0
Name: brynq-sdk-acerta
Version: 1.1.0
Summary: Acerta wrapper from BrynQ
Home-page: UNKNOWN
Author: BrynQ
Author-email: support@brynq.com
License: BrynQ License
Platform: UNKNOWN
